xscen/__init__.py
xscen/aggregate.py
xscen/biasadjust.py
xscen/catalog.py
xscen/catutils.py
xscen/config.py
xscen/diagnostics.py
xscen/ensembles.py
xscen/extract.py
xscen/indicators.py
xscen/io.py
xscen/regrid.py
xscen/scripting.py
xscen/spatial.py
xscen/testing.py
xscen/utils.py
xscen/CVs/frequency_to_timedelta.json
xscen/CVs/frequency_to_xrfreq.json
xscen/CVs/infer_resolution.json
xscen/CVs/resampling_methods.json
xscen/CVs/variable_names.json
xscen/CVs/xrfreq_to_frequency.json
xscen/CVs/xrfreq_to_timedelta.json
xscen/data/IPCC_annual_global_tas.nc
xscen/data/file_schema.yml
xscen/data/fr/LC_MESSAGES/xscen.mo
xscen/data/fr/LC_MESSAGES/xscen.po
xscen/xclim_modules/__init__.py
xscen/xclim_modules/conversions.py
xscen/xclim_modules/conversions.yml
xscen-0.13.1.dist-info/licenses/LICENSE
xscen-0.13.1.dist-info/WHEEL
xscen-0.13.1.dist-info/METADATA
xscen-0.13.1.dist-info/RECORD
