Metadata-Version: 2.4
Name: xscen
Version: 0.13.1
Summary: A climate change scenario-building analysis framework, built with xclim/xarray.
Keywords: xscen
Author-email: Gabriel Rondeau-Genesse <rondeau-genesse.gabriel@ouranos.ca>, Pascal Bourgault <bourgault.pascal@ouranos.ca>, Juliette Lavoie <lavoie.juliette@ouranos.ca>
Maintainer-email: Gabriel Rondeau-Genesse <rondeau-genesse.gabriel@ouranos.ca>, Trevor James Smith <smith.trevorj@ouranos.ca>
Requires-Python: >=3.10.0
License-Expression: Apache-2.0
Classifier: Development Status :: 4 - Beta
Classifier: Intended Audience :: Developers
Classifier: Intended Audience :: Science/Research
Classifier: Natural Language :: English
Classifier: Operating System :: OS Independent
Classifier: Programming Language :: Python :: 3
Classifier: Programming Language :: Python :: 3 :: Only
Classifier: Programming Language :: Python :: 3.10
Classifier: Programming Language :: Python :: 3.11
Classifier: Programming Language :: Python :: 3.12
Classifier: Programming Language :: Python :: 3.13
Classifier: Programming Language :: Python :: Implementation :: CPython
Classifier: Topic :: Scientific/Engineering :: Atmospheric Science
Classifier: Typing :: Typed
License-File: LICENSE
Requires-Dist: cartopy >=0.23.0
Requires-Dist: cftime
Requires-Dist: cf_xarray >=0.7.6
Requires-Dist: clisops >=0.16.1
Requires-Dist: dask >=2024.8.1
Requires-Dist: flox
Requires-Dist: fsspec
Requires-Dist: geopandas >=1.0
Requires-Dist: h5netcdf >=1.5.0
Requires-Dist: h5py >=3.12.1
Requires-Dist: intake-esm ==2025.2.3
Requires-Dist: matplotlib >=3.6
Requires-Dist: netcdf4
Requires-Dist: numcodecs <0.16.0
Requires-Dist: numpy >=1.24
Requires-Dist: openpyxl
Requires-Dist: pandas >=2.2
Requires-Dist: parse
Requires-Dist: pyarrow >=15.0.0
Requires-Dist: pydantic <2.12.0
Requires-Dist: pyproj
Requires-Dist: pyyaml
Requires-Dist: rechunker >=0.5.3
Requires-Dist: scipy >=1.11.0
Requires-Dist: shapely >=2.0
Requires-Dist: sparse
Requires-Dist: toolz
Requires-Dist: xarray >=2023.11.0, !=2024.6.0
Requires-Dist: xclim >=0.56, <0.59
Requires-Dist: xsdba >=0.4.0
Requires-Dist: zarr >=2.13,<3.0
Requires-Dist: xscen[dev] ; extra == "all"
Requires-Dist: xscen[docs] ; extra == "all"
Requires-Dist: xscen[extras] ; extra == "all"
Requires-Dist: babel >=2.17 ; extra == "dev"
Requires-Dist: bump-my-version >=1.2.3 ; extra == "dev"
Requires-Dist: codespell >=2.4.1 ; extra == "dev"
Requires-Dist: coverage >=7.5.0 ; extra == "dev"
Requires-Dist: deptry >=0.23.1 ; extra == "dev"
Requires-Dist: flake8 >=7.3.0 ; extra == "dev"
Requires-Dist: flake8-rst-docstrings >=0.3.1 ; extra == "dev"
Requires-Dist: flit >=3.11.0,<4.0 ; extra == "dev"
Requires-Dist: mypy >=1.18.2 ; extra == "dev"
Requires-Dist: numpydoc >=1.9.0 ; extra == "dev"
Requires-Dist: pip >=25.2 ; extra == "dev"
Requires-Dist: pooch >=1.8.0 ; extra == "dev"
Requires-Dist: pre-commit >=3.5.0 ; extra == "dev"
Requires-Dist: pytest-cov >=5.0.0 ; extra == "dev"
Requires-Dist: pytest >=8.3.2 ; extra == "dev"
Requires-Dist: pytest-xdist[psutil] >=3.2.0 ; extra == "dev"
Requires-Dist: ruff >=0.13.3 ; extra == "dev"
Requires-Dist: tox >=4.30.3 ; extra == "dev"
Requires-Dist: vulture >=2.14 ; extra == "dev"
Requires-Dist: watchdog >=4.0.0 ; extra == "dev"
Requires-Dist: xdoctest ; extra == "dev"
Requires-Dist: yamllint >=1.35.1 ; extra == "dev"
Requires-Dist: ipykernel ; extra == "docs"
Requires-Dist: ipython >=8.5.0 ; extra == "docs"
Requires-Dist: jupyter_client ; extra == "docs"
Requires-Dist: nbsphinx >=0.9.5 ; extra == "docs"
Requires-Dist: nbval ; extra == "docs"
Requires-Dist: sphinx >=7.1.0,<8.2 ; extra == "docs"
Requires-Dist: sphinx-autodoc-typehints ; extra == "docs"
Requires-Dist: sphinx-codeautolink ; extra == "docs"
Requires-Dist: sphinx-copybutton ; extra == "docs"
Requires-Dist: sphinx-intl ; extra == "docs"
Requires-Dist: sphinx-mdinclude ; extra == "docs"
Requires-Dist: sphinx-rtd-theme >=1.0 ; extra == "docs"
Requires-Dist: nc-time-axis >=1.3.1 ; extra == "extras"
Requires-Dist: xscen[xesmf] ; extra == "extras"
Requires-Dist: xesmf >=0.7, !=0.8.8 ; extra == "xesmf"
Project-URL: About Ouranos, https://ouranos.ca/en/
Project-URL: Changelog, https://xscen.readthedocs.io/en/stable/changelog.html
Project-URL: Homepage, https://xscen.readthedocs.io/
Project-URL: Issue tracker, https://github.com/Ouranosinc/xscen/issues
Project-URL: Source, https://github.com/Ouranosinc/xscen
Provides-Extra: all
Provides-Extra: dev
Provides-Extra: docs
Provides-Extra: extras
Provides-Extra: xesmf
